{
  "HAKaSBE3-I6MWER-CQ6ZQF": {
    "user": "Youssef",
    "active": true,
    "expires": "2025-10-04 02:54:38",
    "mac": "90:2E:16:3F:8A:22",
    "ip": "",
    "location": "",
    "online": false,
    "last_online": "Never",
    "created_at": "2025-09-04 02:54:38"
  },
  "HAKaSBE3-12WPZ7-0EEHY7": {
    "user": "Amina",
    "active": true,
    "expires": "2025-10-04 03:01:57",
    "mac": "",
    "ip": "",
    "location": "",
    "online": false,
    "last_online": "Never",
    "created_at": "2025-09-04 03:01:57"
  }
}